AUTHORS.rst
CHANGELOG.rst
LICENSE.rst
MANIFEST.in
README.rst
setup.py
BYONDToolsv3.egg-info/PKG-INFO
BYONDToolsv3.egg-info/SOURCES.txt
BYONDToolsv3.egg-info/dependency_links.txt
BYONDToolsv3.egg-info/requires.txt
BYONDToolsv3.egg-info/top_level.txt
BYONDToolsv3.egg-info/zip-safe
byond/__init__.py
byond/basetypes.py
byond/directions.py
byond/objtree.py
byond/utils.py
byond/world.py
byond/DMI/State.py
byond/DMI/__init__.py
byond/DMI/utils.py
byond/DMIH/Variable.py
byond/DMIH/__init__.py
byond/DMIH/directives/Direction.py
byond/DMIH/directives/Directive.py
byond/DMIH/directives/Import.py
byond/DMIH/directives/State.py
byond/DMIH/directives/__init__.py
byond/data/stdlib/atom_defaults.dm
byond/data/stdlib/dm_std.dm
byond/map/__init__.py
byond/map/format/__init__.py
byond/map/format/base.py
byond/map/format/dmm.py
byond/mapfixes/__init__.py
byond/mapfixes/base.py
byond/mapfixes/ss13.py
byond/mapfixes/ss13_vgstation.py
byond/network/__init__.py
byond/network/packets/__init__.py
byond/script/__init__.py
byond/script/dmscript/__init__.py
scripts/byondtools-postinstall.py
scripts/dmi.py
scripts/dmi_compile.py
scripts/dmindent.py
scripts/dmm.py
scripts/dmmfix.py
scripts/dmmrender.py