Metadata-Version: 1.1
Name: BYONDToolsv3
Version: 0.1.3
Summary: Tools and interfaces for interacting with the BYOND game engine, adapted to Python 3.
Home-page: https://github.com/ComicIronic/BYONDToolsv3
Author: Comic
Author-email: ivb@vanbakel.io
License: MIT
Download-URL: https://github.com/ComicIronic/BYONDToolsv3/tarball/v0.1.3
Platform: UNKNOWN
